lzss.cpython-39-x86_64-linux-gnu.so
include/py3c.h
include/py3c/fileshim.h
include/py3c/tpflags.h
include/py3c/py3shims.h
include/py3c/capsulethunk.h
include/py3c/comparison.h
include/py3c/compat.h
pylzss-0.3.8.dist-info/METADATA
pylzss-0.3.8.dist-info/COPYING.LESSER
pylzss-0.3.8.dist-info/COPYING
pylzss-0.3.8.dist-info/RECORD
pylzss-0.3.8.dist-info/top_level.txt
pylzss-0.3.8.dist-info/WHEEL
