Metadata-Version: 2.1
Name: pylzss
Version: 0.3.8
Summary: A Python library for decoding/encoding LZSS-compressed data.
Author-email: Guillaume Tucker <guillaume.tucker@plasticlogic.com>
Maintainer-email: m1sta <adamhamdi31@gmail.com>
License: LGPL-3.0-only
Project-URL: Repository, https://github.com/m1stadev/pylzss
Project-URL: Bug Tracker, https://github.com/m1stadev/pylzss/issues
Requires-Python: >=3.8
License-File: COPYING
License-File: COPYING.LESSER
